outlier_101703139/outlier.py
outlier_101703139-3.0.0.dist-info/LICENSE
outlier_101703139-3.0.0.dist-info/METADATA
outlier_101703139-3.0.0.dist-info/WHEEL
outlier_101703139-3.0.0.dist-info/entry_points.txt
outlier_101703139-3.0.0.dist-info/top_level.txt
outlier_101703139-3.0.0.dist-info/RECORD
