Metadata-Version: 2.1
Name: outlier-101703139
Version: 3.0.0
Summary: A Python package to remove outliers from a dataset.
Home-page: UNKNOWN
Author: Bharat Chauhan
Author-email: bharatchauhan752000@gmail.com
License: MIT
Platform: UNKNOWN
Classifier: License :: OSI Approved :: MIT License
Classifier: Programming Language :: Python :: 3
Classifier: Programming Language :: Python :: 3.7
Requires-Dist: pandas
